{
  "kind": "collectionType",
  "collectionName": "influencers",
  "info": {
    "singularName": "influencer",
    "pluralName": "influencers",
    "displayName": "Influencer"
  },
  "options": {
    "draftAndPublish": true
  },
  "pluginOptions": {
    "i18n": {
      "localized": true
    }
  },
  "attributes": {
    "name": {
      "type": "string",
      "pluginOptions": {
        "i18n": {
          "localized": true
        }
      },
      "required": true
    },
    "image": {
      "type": "media",
      "pluginOptions": {
        "i18n": {
          "localized": false
        }
      },
      "multiple": true,
      "allowedTypes": [
        "images",
        "videos"
      ]
    },
    "phone": {
      "type": "string",
      "pluginOptions": {
        "i18n": {
          "localized": false
        }
      }
    },
    "email": {
      "type": "email",
      "pluginOptions": {
        "i18n": {
          "localized": false
        }
      }
    },
    "desc": {
      "type": "richtext",
      "pluginOptions": {
        "i18n": {
          "localized": true
        }
      }
    },
    "start_date": {
      "type": "datetime",
      "pluginOptions": {
        "i18n": {
          "localized": false
        }
      },
      "unique": false
    },
    "end_date": {
      "type": "datetime",
      "pluginOptions": {
        "i18n": {
          "localized": false
        }
      }
    },
    "location": {
      "type": "relation",
      "relation": "oneToOne",
      "target": "api::location.location",
      "inversedBy": "influencer"
    },
    "social_media": {
      "type": "component",
      "pluginOptions": {
        "i18n": {
          "localized": false
        }
      },
      "component": "common.social-media",
      "repeatable": true
    },
    "latest_posting": {
      "type": "component",
      "pluginOptions": {
        "i18n": {
          "localized": false
        }
      },
      "component": "influencer.influencer",
      "repeatable": true
    }
  }
}
